gevent_pipeline/__init__.py
gevent_pipeline/closablequeue.py
gevent_pipeline/pipeline.py
gevent_pipeline-0.0.5.dist-info/DESCRIPTION.rst
gevent_pipeline-0.0.5.dist-info/METADATA
gevent_pipeline-0.0.5.dist-info/RECORD
gevent_pipeline-0.0.5.dist-info/WHEEL
gevent_pipeline-0.0.5.dist-info/metadata.json
gevent_pipeline-0.0.5.dist-info/top_level.txt
