Metadata-Version: 2.0
Name: gevent-pipeline
Version: 0.0.5
Summary: Multi-worker pipeline and closable queue
Home-page: https://github.com/simonschmidt/gevent-pipeline
Author: Simon Schmidt
Author-email: schmidt.simon@gmail.com
License: ISC
Keywords: gevent pipelines chaining closablequeue
Platform: UNKNOWN
Classifier: Development Status :: 4 - Beta
Classifier: Intended Audience :: Developers
Classifier: License :: OSI Approved :: ISC License (ISCL)
Classifier: Programming Language :: Python :: 3
Classifier: Programming Language :: Python :: 3.4
Classifier: Programming Language :: Python :: 3.5
Requires-Dist: gevent
